pymc3_models/__init__.py
pymc3_models/exc.py
pymc3_models/models/HierarchicalLogisticRegression.py
pymc3_models/models/LinearRegression.py
pymc3_models/models/__init__.py
pymc3_models-1.1.2.dist-info/DESCRIPTION.rst
pymc3_models-1.1.2.dist-info/METADATA
pymc3_models-1.1.2.dist-info/RECORD
pymc3_models-1.1.2.dist-info/WHEEL
pymc3_models-1.1.2.dist-info/metadata.json
pymc3_models-1.1.2.dist-info/top_level.txt
tests/__init__.py
tests/test_BayesianModel.py
tests/test_HierarchicalLogisticRegression.py
tests/test_LinearRegression.py
tests/models/__init__.py
tests/models/test_BayesianModel.py
tests/models/test_HierarchicalLogisticRegression.py
tests/models/test_LinearRegression.py
