Metadata-Version: 2.0
Name: pymc3-models
Version: 1.1.2
Summary: Custom PyMC3 models built on top of the scikit-learn API
Home-page: https://github.com/parsing-science/pymc3_models
Author: Nicole Carlson
Author-email: nicole@parsingscience.com
License: Apache License
Requires-Dist: joblib
Requires-Dist: matplotlib
Requires-Dist: numpy
Requires-Dist: pandas (>=0.19)
Requires-Dist: pymc3 (>=3.3)
Requires-Dist: scipy
Requires-Dist: seaborn
Requires-Dist: sklearn
